tictactoexxl/__init__.py
tictactoexxl/board.py
tictactoexxl/exception.py
tictactoexxl/game.py
tictactoexxl/grid.py
tictactoexxl/player.py
tictactoexxl/tools.py
tictactoexxl-1.0.1.data/scripts/tictactoexxl-play.py
tictactoexxl-1.0.1.dist-info/DESCRIPTION.rst
tictactoexxl-1.0.1.dist-info/METADATA
tictactoexxl-1.0.1.dist-info/metadata.json
tictactoexxl-1.0.1.dist-info/RECORD
tictactoexxl-1.0.1.dist-info/top_level.txt
tictactoexxl-1.0.1.dist-info/WHEEL
