Metadata-Version: 2.0
Name: tictactoexxl
Version: 1.0.1
Summary: A tic-tac-toe game with xxl fun
Home-page: https://github.com/jordimarinvalle/tictactoexxl
Author: Jordi Marín Valle
Author-email: py.jordi@gmail.com
License: MIT
Keywords: tictactoe,tictactoexxl,game,board game
Platform: all
Classifier: Development Status :: 5 - Production/Stable
Classifier: Environment :: Console
Classifier: Intended Audience :: Developers
Classifier: License :: OSI Approved :: MIT License
Classifier: Programming Language :: Python :: 2
Classifier: Programming Language :: Python :: 2.7
Classifier: Programming Language :: Python :: 3
Classifier: Programming Language :: Python :: 3.4
Classifier: Topic :: Games/Entertainment :: Board Games
Provides-Extra: testing
Requires-Dist: pytest; extra == 'testing'
Requires-Dist: coverage; extra == 'testing'
Requires-Dist: pytest-cov; extra == 'testing'
